oss_pasarela/__init__.py
oss_pasarela/_version.py
oss_pasarela/handlers.py
oss_pasarela-0.1.6.data/data/etc/jupyter/jupyter_notebook_config.d/oss_pasarela.json
oss_pasarela-0.1.6.data/data/etc/jupyter/jupyter_server_config.d/oss_pasarela.json
oss_pasarela-0.1.6.data/data/share/jupyter/labextensions/oss-pasarela/build_log.json
oss_pasarela-0.1.6.data/data/share/jupyter/labextensions/oss-pasarela/package.json
oss_pasarela-0.1.6.data/data/share/jupyter/labextensions/oss-pasarela/static/lib_index_js.9feca078e5241d7e8936.js
oss_pasarela-0.1.6.data/data/share/jupyter/labextensions/oss-pasarela/static/lib_index_js.9feca078e5241d7e8936.js.map
oss_pasarela-0.1.6.data/data/share/jupyter/labextensions/oss-pasarela/static/remoteEntry.b1069290a0d760f6c8d9.js
oss_pasarela-0.1.6.data/data/share/jupyter/labextensions/oss-pasarela/static/remoteEntry.b1069290a0d760f6c8d9.js.map
oss_pasarela-0.1.6.data/data/share/jupyter/labextensions/oss-pasarela/static/style.js
oss_pasarela-0.1.6.data/data/share/jupyter/labextensions/oss-pasarela/static/style_index_js.d864bbcd3d7a42abcce5.js
oss_pasarela-0.1.6.data/data/share/jupyter/labextensions/oss-pasarela/static/style_index_js.d864bbcd3d7a42abcce5.js.map
oss_pasarela-0.1.6.data/data/share/jupyter/labextensions/oss-pasarela/static/vendors-node_modules_bootstrap_dist_css_bootstrap_min_css.bd408c9a32d8e876e4ae.js
oss_pasarela-0.1.6.data/data/share/jupyter/labextensions/oss-pasarela/static/vendors-node_modules_bootstrap_dist_css_bootstrap_min_css.bd408c9a32d8e876e4ae.js.map
oss_pasarela-0.1.6.data/data/share/jupyter/labextensions/oss-pasarela/static/vendors-node_modules_css-loader_dist_runtime_api_js-node_modules_css-loader_dist_runtime_cssW-72eba1.986066191fbefa152f6c.js
oss_pasarela-0.1.6.data/data/share/jupyter/labextensions/oss-pasarela/static/vendors-node_modules_css-loader_dist_runtime_api_js-node_modules_css-loader_dist_runtime_cssW-72eba1.986066191fbefa152f6c.js.map
oss_pasarela-0.1.6.dist-info/METADATA
oss_pasarela-0.1.6.dist-info/WHEEL
oss_pasarela-0.1.6.dist-info/licenses/LICENSE
oss_pasarela-0.1.6.dist-info/RECORD
