Metadata-Version: 2.1
Name: oss-pasarela
Version: 0.1.6
Summary: A JupyterLab extension to open notebooks from websites with just one click.
Project-URL: Homepage, https://github.com/Navteca/oss-pasarela.git
Project-URL: Bug Tracker, https://github.com/Navteca/oss-pasarela.git/issues
Project-URL: Repository, https://github.com/Navteca/oss-pasarela.git.git
Author-email: Navteca LLC <info@navteca.com>
License: BSD 3-Clause License
License-File: LICENSE
Classifier: Framework :: Jupyter
Classifier: Framework :: Jupyter :: JupyterLab
Classifier: Framework :: Jupyter :: JupyterLab :: 3
Classifier: Framework :: Jupyter :: JupyterLab :: Extensions
Classifier: Framework :: Jupyter :: JupyterLab :: Extensions :: Prebuilt
Classifier: License :: OSI Approved :: BSD License
Classifier: Programming Language :: Python
Classifier: Programming Language :: Python :: 3
Classifier: Programming Language :: Python :: 3.7
Classifier: Programming Language :: Python :: 3.8
Classifier: Programming Language :: Python :: 3.9
Classifier: Programming Language :: Python :: 3.10
Classifier: Programming Language :: Python :: 3.11
Requires-Python: >=3.8
Requires-Dist: jupyter-server
Requires-Dist: validators>=0.20.0
